{
    "impermanence": {
        "branch": "master",
        "description": "Modules to help you handle persistent state on systems with ephemeral root storage [maintainer=@talyz]",
        "homepage": "",
        "owner": "nix-community",
        "repo": "impermanence",
        "rev": "e3a7acd113903269a1b5c8b527e84ce7ee859851",
        "sha256": "1kypb376fyxqb1nn65j579nm5cl5cyrhghcbf2ajgpdpszbv728q",
        "type": "tarball",
        "url": "https://github.com/nix-community/impermanence/archive/e3a7acd113903269a1b5c8b527e84ce7ee859851.tar.gz",
        "url_template": "https://github.com/<owner>/<repo>/archive/<rev>.tar.gz"
    },
    "lanzaboote": {
        "branch": "v0.3.0",
        "description": "Secure Boot for NixOS [maintainers=@blitz @raitobezarius @nikstur]",
        "homepage": "",
        "owner": "nix-community",
        "repo": "lanzaboote",
        "rev": "64b903ca87d18cef2752c19c098af275c6e51d63",
        "sha256": "1ysq47isagsdaisni4sbhhmbmihbhpgxj8lnzxl4kgfx2iwm7ghm",
        "type": "tarball",
        "url": "https://github.com/nix-community/lanzaboote/archive/64b903ca87d18cef2752c19c098af275c6e51d63.tar.gz",
        "url_template": "https://github.com/<owner>/<repo>/archive/<rev>.tar.gz"
    },
    "nixos-23.05": {
        "branch": "nixos-23.05",
        "description": "Nix Packages collection",
        "homepage": "",
        "owner": "NixOS",
        "repo": "nixpkgs",
        "rev": "e5f018cf150e29aac26c61dac0790ea023c46b24",
        "sha256": "18jlakvhnbvaxgggimw1qpikdwdkz9yhwiv4hmns4sr2ab7lrg27",
        "type": "tarball",
        "url": "https://github.com/NixOS/nixpkgs/archive/e5f018cf150e29aac26c61dac0790ea023c46b24.tar.gz",
        "url_template": "https://github.com/<owner>/<repo>/archive/<rev>.tar.gz"
    },
    "nixos-hardware": {
        "branch": "master",
        "description": "A collection of NixOS modules covering hardware quirks.",
        "homepage": "",
        "owner": "nixos",
        "repo": "nixos-hardware",
        "rev": "3ccd87fcdae4732fe33773cefa4375c641a057e7",
        "sha256": "0gnh8zc4j4qbcby1hgnqc8mg66mcicqxpi5rrdg0xya7crfgpwrl",
        "type": "tarball",
        "url": "https://github.com/nixos/nixos-hardware/archive/3ccd87fcdae4732fe33773cefa4375c641a057e7.tar.gz",
        "url_template": "https://github.com/<owner>/<repo>/archive/<rev>.tar.gz"
    },
    "nixpkgs-unstable": {
        "branch": "nixpkgs-unstable",
        "description": "Nix Packages collection",
        "homepage": "",
        "owner": "NixOS",
        "repo": "nixpkgs",
        "rev": "1697b7d480449b01111e352021f46e5879e47643",
        "sha256": "1k9ladmxid95n9hxdpzgsrkrmmrz78y3212r1idxzx3ckr0qh9jr",
        "type": "tarball",
        "url": "https://github.com/NixOS/nixpkgs/archive/1697b7d480449b01111e352021f46e5879e47643.tar.gz",
        "url_template": "https://github.com/<owner>/<repo>/archive/<rev>.tar.gz"
    },
    "pre-commit-hooks.nix": {
        "branch": "master",
        "description": "Seamless integration of https://pre-commit.com git hooks with Nix.",
        "homepage": "",
        "owner": "cachix",
        "repo": "pre-commit-hooks.nix",
        "rev": "4f883a76282bc28eb952570afc3d8a1bf6f481d7",
        "sha256": "1ahkfgz39jglhs5svmmm04hbk5wyq2ph620wa7qqb9d8594639x1",
        "type": "tarball",
        "url": "https://github.com/cachix/pre-commit-hooks.nix/archive/4f883a76282bc28eb952570afc3d8a1bf6f481d7.tar.gz",
        "url_template": "https://github.com/<owner>/<repo>/archive/<rev>.tar.gz"
    }
}
